chaos_maps/__init__.py
chaos_maps/chaotic_maps.py
chaos_maps/chaotic_maps_test.py
chaos_maps/plotting/__init__.py
chaos_maps/plotting/plotting.py
chaos_maps/plotting/plotting_test.py
chaos_maps/plotting/plt_config.py
chaos_maps-0.4.0.dist-info/LICENSE
chaos_maps-0.4.0.dist-info/METADATA
chaos_maps-0.4.0.dist-info/WHEEL
chaos_maps-0.4.0.dist-info/top_level.txt
chaos_maps-0.4.0.dist-info/RECORD
