Metadata-Version: 2.1
Name: chaos-maps
Version: 0.4.0
Summary: A package for studying and visualizing the dynamical behavior of chaotic maps
Home-page: https://github.com/iokaf/discrete_chaos
Author: Dr. Ioannis Kafetzis
Author-email: ioanniskaf@gmail.com
License: MIT
Keywords: chaotic maps bifurcations Lyapunov exponents
Classifier: Programming Language :: Python :: 3
Classifier: License :: OSI Approved :: MIT License
Classifier: Operating System :: OS Independent
Requires-Python: >=3.6
License-File: LICENSE
Requires-Dist: numpy
Requires-Dist: matplotlib
